.gitignore
.mergify.yml
.pre-commit-config.yaml
.travis.yml
AUTHORS
README.md
pyproject.toml
setup.cfg
setup.py
LICENSES/LGPL-2.1-or-later.txt
LICENSES/MIT.txt
cython_sgio.egg-info/PKG-INFO
cython_sgio.egg-info/SOURCES.txt
cython_sgio.egg-info/dependency_links.txt
cython_sgio.egg-info/requires.txt
cython_sgio.egg-info/top_level.txt
src/linux_sgio.c
src/linux_sgio.pyx