Metadata-Version: 2.1
Name: cython-sgio
Version: 1.1.2
Summary: Cython-based wrapper for sending SCSI Generic I/O commands from Python.
Home-page: https://github.com/python-scsi/cython-sgio
Maintainer: Diego Elio Pettenò
Maintainer-email: flameeyes@flameeyes.com
License: LGPL-2.1+
Keywords: scsi
Platform: linux
Classifier: Programming Language :: Python
Classifier: Programming Language :: Python :: 3
Classifier: Development Status :: 4 - Beta
Classifier: License :: OSI Approved :: GNU Lesser General Public License v2 or later (LGPLv2+)
Provides-Extra: dev
